[
  {
    "id": 1,
    "slug": 1,
    "title": "ブログを作ろう！",
    "summary": "ブログ作成",
    "date": "2025-05-06T09:57:22.000Z",
    "category": "Project",
    "tags": "{\"ブログ\",\"開始\"}"
  },
  {
    "id": 2,
    "slug": 2,
    "title": "1.ブログの環境構築",
    "summary": "ブログ作成のための環境構築過程",
    "date": "2025-05-06T22:44:20.000Z",
    "category": "Project",
    "tags": "{\"ブログ\",\"環境選定\",\"環境構築\"}"
  },
  {
    "id": 3,
    "slug": 3,
    "title": "2.WebCSSの基本知識",
    "summary": "ブログを作成する前の基本知識",
    "date": "2025-05-07T11:47:55.000Z",
    "category": "Project",
    "tags": "{\"ブログ\",\"Frontend\"}"
  },
  {
    "id": 4,
    "slug": 4,
    "title": "3.ブログ初期構成と実装(GitHub Pages → Vercel 移行前）",
    "summary": "ブログの初期構成",
    "date": "2025-05-07T12:40:23.000Z",
    "category": "Project",
    "tags": "{\"ブログ\",\"初期構成\"}"
  },
  {
    "id": 5,
    "slug": 5,
    "title": "4.GitHub PagesからVercelに移行",
    "summary": "GitHub PagesからVercelに移行",
    "date": "2025-05-07T13:01:16.000Z",
    "category": "Project",
    "tags": "{\"ブログ\",\"devOps\",\"移行\"}"
  },
  {
    "id": 6,
    "slug": 6,
    "title": "5.ブログの骨組みが整った記録",
    "summary": "ブログの骨組みについて",
    "date": "2025-05-07T13:47:32.000Z",
    "category": "Project",
    "tags": "{\"ブログ\",\"骨組み構築\"}"
  },
  {
    "id": 7,
    "slug": 7,
    "title": "ブログデザイン周りについて",
    "summary": "デザインについて。。",
    "date": "2025-05-11T14:38:08.000Z",
    "category": "Project",
    "tags": "{\"ブログ\",\"Frontend\",\"デザイン\"}"
  },
  {
    "id": 8,
    "slug": 8,
    "title": "エンジニアとして気づいたこと、そしてこのブログを始めた理由",
    "summary": "開発について雑談",
    "date": "2025-05-18T14:49:29.000Z",
    "category": "Career & Life",
    "tags": "{\"雑談\",\"開発\"}"
  },
  {
    "id": 9,
    "slug": 9,
    "title": "ブログ運営とデータベース導入に関する検討記録",
    "summary": "DB導入",
    "date": "2025-05-27T13:41:04.000Z",
    "category": "Project",
    "tags": "{\"ブログ\",\"Database\",\"Tips\"}"
  },
  {
    "id": 10,
    "slug": 10,
    "title": "🌟今後の目標&プロジェクトに関する悩み。。",
    "summary": "新プロジェクト",
    "date": "2025-06-14T11:54:55.000Z",
    "category": "Project",
    "tags": "{\"新プロジェクト\",\"悩み\"}"
  },
  {
    "id": 11,
    "slug": 11,
    "title": "アプリ開発プロジェクトの構想",
    "summary": "アプリ開発/構想",
    "date": "2025-06-15T09:24:04.000Z",
    "category": "App Project①",
    "tags": "{\"App開発\",\"構想\"}"
  },
  {
    "id": 12,
    "slug": 12,
    "title": "開発環境管理ツール、Dockerの導入",
    "summary": "Dokerの導入",
    "date": "2025-06-22T14:28:12.000Z",
    "category": "Project",
    "tags": "{\"Docker\",\"開発環境\"}"
  },
  {
    "id": 13,
    "slug": 13,
    "title": "Flutter開発環境構築まとめ",
    "summary": "App開発の環境構築",
    "date": "2025-06-30T09:38:09.000Z",
    "category": "App Project①",
    "tags": "{\"App\",\"環境構築\"}"
  },
  {
    "id": 14,
    "slug": 14,
    "title": "NAS導入について",
    "summary": "NAS導入の悩み",
    "date": "2025-07-05T15:03:58.000Z",
    "category": "Project",
    "tags": "{\"開発環境、NAS\"}"
  }
]